{"skeleton":{"hash":"HL0z2PZZ3hi0f980jFmCHpvBJU4","spine":"2.1.20","width":181,"height":445.5,"images":"./../animation/images/"},"bones":[{"name":"root","x":-220,"color":"ffffffff"},{"name":"effect_back","parent":"root","x":115.87,"y":128.09,"color":"ffffffff"},{"name":"effect_front","parent":"root","x":115.87,"y":128.09,"color":"ffffffff"},{"name":"hip","parent":"root","y":133.01,"color":"ffffffff"},{"name":"L_leg_1","parent":"hip","length":8.28,"x":-18.5,"y":-11.51,"rotation":-90,"color":"ffc900ff"},{"name":"R_leg_1","parent":"hip","length":8.28,"x":18.5,"y":-11.51,"rotation":-90,"color":"00e004ff"},{"name":"hip_skirt_rot","parent":"hip","y":-0.01,"rotation":45},{"name":"skirt_a1","parent":"hip","length":53.26,"x":0.89,"y":-4.71,"rotation":-102.97,"color":"530054ff"},{"name":"skirt_a2","parent":"hip","length":53.26,"x":0.89,"y":-4.71,"rotation":244,"color":"a800abff"},{"name":"skirt_b1","parent":"hip","length":53.26,"x":0.89,"y":-4.71,"rotation":-77.84,"color":"66000eff"},{"name":"skirt_b2","parent":"hip","length":53.26,"x":0.89,"y":-4.71,"rotation":294,"color":"c2001aff"},{"name":"skirt_front","parent":"hip","length":53.26,"x":0.89,"y":-4.71,"rotation":-90,"color":"fff700ff"},{"name":"torso","parent":"hip","length":104.38,"y":3.85,"rotation":90},{"name":"L_arm_01","parent":"torso","length":8.27,"x":106.68,"y":32.43,"rotation":161.83,"color":"069b00ff"},{"name":"L_leg_2","parent":"L_leg_1","length":8.28,"x":8.05,"color":"ffc900ff"},{"name":"R_arm_01","parent":"torso","length":8.27,"x":106.68,"y":-27.93,"scaleX":0.977,"scaleY":0.977,"rotation":-161.94,"color":"ff9100ff"},{"name":"R_leg_2","parent":"R_leg_1","length":8.28,"x":8.05,"color":"00e004ff"},{"name":"hood","parent":"torso","x":107.82,"y":10.9},{"name":"neck","parent":"torso","length":33.93,"x":104.5},{"name":"skirt_a1_low","parent":"skirt_a1","length":72.6,"x":51.67,"y":11.83,"rotation":12.97,"color":"530054ff"},{"name":"skirt_a2_low","parent":"skirt_a2","length":72.6,"x":47.66,"y":23.2,"rotation":26,"color":"a800abff"},{"name":"skirt_b1_low","parent":"skirt_b1","length":72.6,"x":51.81,"y":-11.21,"rotation":-12.15,"color":"66000eff"},{"name":"skirt_b2_low","parent":"skirt_b2","length":72.61,"x":48.4,"y":-21.6,"scaleY":0.999,"rotation":-24,"color":"c2001aff"},{"name":"skirt_front_low","parent":"skirt_front","length":72.61,"x":53.01,"y":-0.04,"color":"fff700ff"},{"name":"tie","parent":"torso","x":107.82,"y":-14.76},{"name":"L_arm_02","parent":"L_arm_01","length":8.27,"x":8.4,"rotation":1.82,"color":"069b00ff"},{"name":"L_leg_3","parent":"L_leg_2","length":8.28,"x":8.79,"color":"ffc900ff"},{"name":"R_arm_02","parent":"R_arm_01","length":8.27,"x":8.4,"rotation":-1.58,"color":"ff9100ff"},{"name":"R_leg_3","parent":"R_leg_2","length":8.28,"x":8.79,"color":"00e004ff"},{"name":"head","parent":"neck","length":150.12,"x":33.86},{"name":"L_arm_03","parent":"L_arm_02","length":8.27,"x":8.39,"rotation":1.82,"color":"069b00ff"},{"name":"L_leg_4","parent":"L_leg_3","length":8.28,"x":8.1,"color":"ffc900ff"},{"name":"R_arm_03","parent":"R_arm_02","length":8.27,"x":8.39,"rotation":-1.58,"color":"ff9100ff"},{"name":"R_leg_4","parent":"R_leg_3","length":8.28,"x":8.1,"color":"00e004ff"},{"name":"b_hair","parent":"head","x":119.39,"y":-0.05,"color":"b56f3aff"},{"name":"hair_a","parent":"head","x":120.28,"y":57.3},{"name":"hair_b","parent":"head","x":120.28,"y":-51.74},{"name":"head_center","parent":"head","x":77.01,"y":-0.44,"color":"000000ff"},{"name":"L_arm_04","parent":"L_arm_03","length":8.27,"x":8.23,"rotation":1.82,"color":"069b00ff"},{"name":"L_earring","parent":"head_center","x":-34.48,"y":72.69,"color":"ff00f8ff"},{"name":"L_leg_5","parent":"L_leg_4","length":8.28,"x":8.58,"color":"ffc900ff"},{"name":"R_arm_04","parent":"R_arm_03","length":8.27,"x":8.23,"rotation":-1.58,"color":"ff9100ff"},{"name":"R_earring","parent":"head_center","x":-34.48,"y":-70.08,"color":"ff00f8ff"},{"name":"R_leg_5","parent":"R_leg_4","length":8.28,"x":8.58,"color":"00e004ff"},{"name":"hat","parent":"head_center","x":58.3,"y":-98.15},{"name":"look","parent":"head_center","x":-17.3,"y":-27.26,"color":"fbff00ff"},{"name":"L_arm_05","parent":"L_arm_04","length":8.27,"x":8.03,"rotation":1.82,"color":"069b00ff"},{"name":"L_eye","parent":"look","x":4.56,"y":61.02,"color":"d96f00ff"},{"name":"L_leg_6","parent":"L_leg_5","length":8.28,"x":8.28,"color":"ffc900ff"},{"name":"R_arm_05","parent":"R_arm_04","length":8.27,"x":8.03,"rotation":-1.58,"color":"ff9100ff"},{"name":"R_eye","parent":"look","x":4.17,"y":-70.52,"color":"00cc00ff"},{"name":"R_leg_6","parent":"R_leg_5","length":8.28,"x":8.28,"color":"00e004ff"},{"name":"blush_L","parent":"look","x":-18.07,"y":61.62,"color":"ff0001ff"},{"name":"blush_R","parent":"look","x":-16.4,"y":-38.78,"scaleX":0.662,"scaleY":0.502,"rotation":-17.05,"color":"ff0001ff"},{"name":"chin","parent":"look","x":-57.69,"y":8.32,"rotation":-83.72,"color":"d6a400ff"},{"name":"glasses","parent":"look","x":-6.47,"y":-12.93,"color":"4ea3f2ff"},{"name":"hair_front_a","parent":"look","x":88.24,"y":-7.29,"color":"ff9a00ff"},{"name":"mouth_lower","parent":"look","x":-35.27,"y":7.89,"rotation":-90,"color":"00049bff"},{"name":"mouth_shapes","parent":"look","x":-27.97,"y":18.66,"color":"62b300ff"},{"name":"mouth_upper","parent":"look","x":-35.27,"y":7.89,"rotation":-90,"color":"a60800ff"},{"name":"tongue","parent":"look","x":-22.78,"y":-0.69,"color":"9b0006ff"},{"name":"L_arm_06","parent":"L_arm_05","length":8.27,"x":8.62,"rotation":1.82,"color":"069b00ff"},{"name":"L_eyebrow_1","parent":"L_eye","length":5.29,"x":24.54,"y":-9.98,"rotation":-81.8,"color":"d96f00ff"},{"name":"L_eyebug","parent":"L_eye","x":0.1,"y":-28.62,"color":"3d1a00ff"},{"name":"L_eyelid_lo","parent":"L_eye","x":-17.99,"y":-15.51,"color":"d9b55cff"},{"name":"L_eyelid_up","parent":"L_eye","x":13.84,"y":-13.46,"color":"d9b55cff"},{"name":"L_leg_7","parent":"L_leg_6","length":8.28,"x":8.14,"color":"ffc900ff"},{"name":"L_mouth_lo_1","parent":"mouth_lower","length":5.29,"x":-2.68,"y":-0.03,"rotation":177.24,"color":"00049bff"},{"name":"L_mouth_up_1","parent":"mouth_upper","length":5.29,"x":-2.68,"y":-0.03,"rotation":177.24,"color":"a60800ff"},{"name":"R_arm_06","parent":"R_arm_05","length":8.27,"x":8.62,"rotation":-1.58,"color":"ff9100ff"},{"name":"R_eyebrow_1","parent":"R_eye","length":5.29,"x":24.93,"y":18.71,"scaleX":0.87,"rotation":82,"color":"00cc00ff"},{"name":"R_eyebug","parent":"R_eye","x":0.63,"y":39.76,"color":"3d1a00ff"},{"name":"R_eyelid_lo","parent":"R_eye","x":-17.61,"y":30.53,"color":"9dcc93ff"},{"name":"R_eyelid_up","parent":"R_eye","x":14.22,"y":28.92,"color":"9dcc93ff"},{"name":"R_leg_7","parent":"R_leg_6","length":8.28,"x":8.14,"color":"00e004ff"},{"name":"R_mouth_lo_1","parent":"mouth_lower","length":5.29,"x":2.02,"y":-0.03,"rotation":3.56,"color":"00049bff"},{"name":"R_mouth_up_1","parent":"mouth_upper","length":5.29,"x":2.02,"y":-0.03,"rotation":3.56,"color":"a60800ff"},{"name":"glasses_b","parent":"glasses","x":14.76,"y":4.87,"color":"1f43baff"},{"name":"hair_front_b","parent":"hair_front_a","x":-4.75,"color":"fbffa6ff"},{"name":"L_arm_07","parent":"L_arm_06","length":8.27,"x":8.42,"rotation":1.82,"color":"069b00ff"},{"name":"L_eye_light","parent":"L_eyebug","x":2.9,"y":-2.1,"color":"ffffffff"},{"name":"L_eye_ref","parent":"L_eyebug","x":-2.71,"y":4.67,"color":"ffffffff"},{"name":"L_eyebrow_2","parent":"L_eyebrow_1","length":5.29,"x":5.29,"rotation":-1.8,"color":"d96f00ff"},{"name":"L_leg_8","parent":"L_leg_7","length":8.28,"x":8.33,"color":"ffc900ff"},{"name":"L_mouth_lo_2","parent":"L_mouth_lo_1","length":5.29,"x":5.4,"rotation":-2.67,"color":"00049bff"},{"name":"L_mouth_up_2","parent":"L_mouth_up_1","length":5.29,"x":5.4,"rotation":-2.67,"color":"a60800ff"},{"name":"R_arm_07","parent":"R_arm_06","length":8.27,"x":8.42,"rotation":-1.58,"color":"ff9100ff"},{"name":"R_eye_light","parent":"R_eyebug","x":2.62,"y":-2.52,"color":"ffffffff"},{"name":"R_eye_ref","parent":"R_eyebug","x":-3,"y":4.43,"color":"ffffffff"},{"name":"R_eyebrow_2","parent":"R_eyebrow_1","length":5.29,"x":5.29,"rotation":1.8,"color":"00cc00ff"},{"name":"R_leg_8","parent":"R_leg_7","length":8.28,"x":8.33,"color":"00e004ff"},{"name":"R_mouth_lo_2","parent":"R_mouth_lo_1","length":5.29,"x":5.4,"rotation":3.56,"color":"00049bff"},{"name":"R_mouth_up_2","parent":"R_mouth_up_1","length":5.29,"x":5.4,"rotation":3.56,"color":"a60800ff"},{"name":"L_arm_08","parent":"L_arm_07","length":8.88,"x":8.32,"rotation":1.82,"color":"069b00ff"},{"name":"L_eyebrow_3","parent":"L_eyebrow_2","length":5.29,"x":5.4,"rotation":-1.8,"color":"d96f00ff"},{"name":"L_leg_9","parent":"L_leg_8","length":8.28,"x":8.03,"color":"ffc900ff"},{"name":"L_mouth_lo_3","parent":"L_mouth_lo_2","length":5.29,"x":5.29,"rotation":-2.67,"color":"00049bff"},{"name":"L_mouth_up_3","parent":"L_mouth_up_2","length":5.29,"x":5.29,"rotation":-2.67,"color":"a60800ff"},{"name":"R_arm_08","parent":"R_arm_07","length":8.27,"x":8.32,"rotation":-1.58,"color":"ff9100ff"},{"name":"R_eyebrow_3","parent":"R_eyebrow_2","length":5.29,"x":5.4,"rotation":1.8,"color":"00cc00ff"},{"name":"R_leg_9","parent":"R_leg_8","length":8.28,"x":8.03,"color":"00e004ff"},{"name":"R_mouth_lo_3","parent":"R_mouth_lo_2","length":5.29,"x":5.29,"rotation":3.56,"color":"00049bff"},{"name":"R_mouth_up_3","parent":"R_mouth_up_2","length":5.29,"x":5.29,"rotation":3.56,"color":"a60800ff"},{"name":"L_arm_09","parent":"L_arm_08","length":8.27,"x":7.93,"rotation":1.82,"color":"069b00ff"},{"name":"L_eyebrow_4","parent":"L_eyebrow_3","length":5.29,"x":5.29,"rotation":-1.8,"color":"d96f00ff"},{"name":"L_leg_10","parent":"L_leg_9","length":8.28,"x":8.43,"color":"ffc900ff"},{"name":"L_mouth_lo_4","parent":"L_mouth_lo_3","length":5.29,"x":5.29,"rotation":-2.67,"color":"00049bff"},{"name":"L_mouth_up_4","parent":"L_mouth_up_3","length":5.29,"x":5.29,"rotation":-2.67,"color":"a60800ff"},{"name":"R_arm_09","parent":"R_arm_08","length":8.27,"x":7.93,"rotation":-1.58,"color":"ff9100ff"},{"name":"R_eyebrow_4","parent":"R_eyebrow_3","length":5.29,"x":5.29,"rotation":1.8,"color":"00cc00ff"},{"name":"R_leg_10","parent":"R_leg_9","length":8.28,"x":8.43,"color":"00e004ff"},{"name":"R_mouth_lo_4","parent":"R_mouth_lo_3","length":5.29,"x":5.29,"rotation":3.56,"color":"00049bff"},{"name":"R_mouth_up_4","parent":"R_mouth_up_3","length":5.29,"x":5.29,"rotation":3.56,"color":"a60800ff"},{"name":"L_arm_10","parent":"L_arm_09","length":8.27,"x":8.32,"rotation":1.82,"color":"069b00ff"},{"name":"L_eyebrow_5","parent":"L_eyebrow_4","length":5.29,"x":5.29,"rotation":-1.8,"color":"d96f00ff"},{"name":"L_leg_11","parent":"L_leg_10","length":8.28,"x":8.43,"color":"ffc900ff"},{"name":"L_mouth_lo_5","parent":"L_mouth_lo_4","length":5.29,"x":5.27,"rotation":-2.67,"color":"00049bff"},{"name":"L_mouth_up_5","parent":"L_mouth_up_4","length":5.29,"x":5.27,"rotation":-2.67,"color":"a60800ff"},{"name":"R_arm_10","parent":"R_arm_09","length":8.27,"x":8.32,"rotation":-1.58,"color":"ff9100ff"},{"name":"R_eyebrow_5","parent":"R_eyebrow_4","length":5.29,"x":5.29,"rotation":1.8,"color":"00cc00ff"},{"name":"R_leg_11","parent":"R_leg_10","length":8.28,"x":8.43,"color":"00e004ff"},{"name":"R_mouth_lo_5","parent":"R_mouth_lo_4","length":5.29,"x":5.33,"rotation":3.56,"color":"00049bff"},{"name":"R_mouth_up_5","parent":"R_mouth_up_4","length":5.29,"x":5.33,"rotation":3.56,"color":"a60800ff"},{"name":"L_arm_11","parent":"L_arm_10","length":8.27,"x":8.52,"rotation":1.82,"color":"069b00ff"},{"name":"L_eyebrow_6","parent":"L_eyebrow_5","length":5.29,"x":5.29,"rotation":-1.8,"color":"d96f00ff"},{"name":"L_leg_12","parent":"L_leg_11","length":8.28,"x":8.33,"color":"ffc900ff"},{"name":"R_arm_11","parent":"R_arm_10","length":8.27,"x":8.52,"rotation":-1.58,"color":"ff9100ff"},{"name":"R_eyebrow_6","parent":"R_eyebrow_5","length":5.29,"x":5.29,"rotation":1.8,"color":"00cc00ff"},{"name":"R_leg_12","parent":"R_leg_11","length":8.28,"x":8.33,"color":"00e004ff"},{"name":"L_arm_12","parent":"L_arm_11","length":8.27,"x":8.23,"rotation":1.82,"color":"069b00ff"},{"name":"L_eyebrow_7","parent":"L_eyebrow_6","length":5.29,"x":5.37,"rotation":-1.8,"color":"d96f00ff"},{"name":"L_leg_13","parent":"L_leg_12","length":8.28,"x":8.13,"color":"ffc900ff"},{"name":"R_arm_12","parent":"R_arm_11","length":8.27,"x":8.23,"rotation":-1.58,"color":"ff9100ff"},{"name":"R_eyebrow_7","parent":"R_eyebrow_6","length":5.29,"x":5.37,"rotation":1.8,"color":"00cc00ff"},{"name":"R_leg_13","parent":"R_leg_12","length":8.28,"x":8.13,"color":"00e004ff"},{"name":"L_arm_13","parent":"L_arm_12","length":8.27,"x":8.37,"rotation":1.82,"color":"069b00ff"},{"name":"L_leg_end","parent":"L_leg_13","length":8.28,"x":8.74,"color":"ffc900ff"},{"name":"R_arm_13","parent":"R_arm_12","length":8.27,"x":8.37,"rotation":-1.58,"color":"ff9100ff"},{"name":"R_leg_end","parent":"R_leg_13","length":8.28,"x":8.74,"color":"00e004ff"},{"name":"L_arm_14","parent":"L_arm_13","length":8.27,"x":8.37,"rotation":1.82,"color":"069b00ff"},{"name":"R_arm_14","parent":"R_arm_13","length":8.27,"x":8.37,"rotation":-1.58,"color":"ff9100ff"},{"name":"L_arm_15","parent":"L_arm_14","length":8.27,"x":8.36,"rotation":1.82,"color":"069b00ff"},{"name":"R_arm_15","parent":"R_arm_14","length":8.27,"x":8.36,"rotation":-1.58,"color":"ff9100ff"},{"name":"L_arm_16","parent":"L_arm_15","length":8.27,"x":8.01,"rotation":1.82,"color":"069b00ff"},{"name":"R_arm_16","parent":"R_arm_15","length":8.27,"x":8.01,"scaleX":1.022,"scaleY":1.022,"rotation":-1.58,"color":"ff9100ff"},{"name":"L_wrist","parent":"L_arm_16","x":7.06,"y":0.09,"rotation":-1.64,"color":"00549bff"},{"name":"R_wrist","parent":"R_arm_16","x":7.06,"y":0.23,"rotation":1.54,"color":"ff0800ff"},{"name":"L_object","parent":"L_wrist","x":17.4,"y":-0.03,"color":"ff7b00ff"},{"name":"R_object","parent":"R_wrist","x":15.97,"y":-0.03,"rotation":359.99,"color":"34ff2bff"},{"name":"finger_1_a2","parent":"R_wrist","length":3.32,"x":20.96,"y":-3.4,"color":"ffd48bff"},{"name":"finger_1_a22","parent":"R_wrist","length":3.24,"x":21.07,"y":3.19,"rotation":-4.95,"color":"fff000ff"},{"name":"finger_1_a23","parent":"L_wrist","length":3.32,"x":21.61,"y":2.47,"rotation":1.36,"color":"069b00ff"},{"name":"finger_1_a24","parent":"L_wrist","length":3.41,"x":21.45,"y":-2.7,"rotation":8.57,"color":"5a9b78ff"},{"name":"finger_2_a","parent":"R_wrist","length":4.57,"x":21.05,"y":-0.05,"color":"ff3f00ff"},{"name":"finger_2_a2","parent":"L_wrist","length":4.68,"x":21.54,"y":-0.09,"rotation":5.39,"color":"00549bff"},{"name":"hand2","parent":"R_wrist","length":18.16,"y":-0.02,"color":"ff0800ff"},{"name":"hand22","parent":"L_wrist","length":18.52,"y":-0.03,"color":"00549bff"},{"name":"thumb_a","parent":"R_wrist","length":9.33,"x":5.89,"y":2.22,"rotation":18.29,"color":"ff9100ff"},{"name":"thumb_a2","parent":"L_wrist","length":9.39,"x":7.17,"y":0.73,"rotation":30.76,"color":"848c00ff"},{"name":"finger_1_b","parent":"finger_1_a2","length":3.45,"x":3.56,"y":0.05,"rotation":-0.9,"color":"ffd48bff"},{"name":"finger_1_b2","parent":"finger_1_a22","length":3.47,"x":3.52,"rotation":-5.39,"color":"fff000ff"},{"name":"finger_1_b3","parent":"finger_1_a23","length":3.59,"x":3.51,"y":-0.03,"rotation":-0.9,"color":"069b00ff"},{"name":"finger_1_b4","parent":"finger_1_a24","length":3.58,"x":3.63,"y":0.02,"rotation":7.18,"color":"5a9b78ff"},{"name":"finger_2_b","parent":"finger_2_a","length":4.57,"x":4.53,"rotation":-0.45,"color":"ff3f00ff"},{"name":"finger_2_b2","parent":"finger_2_a2","length":4.66,"x":4.62,"y":-0.03,"rotation":4.86,"color":"00549bff"},{"name":"thumb_b","parent":"thumb_a","length":8.2,"x":9.73,"y":-0.02,"rotation":-5.84,"color":"ff9100ff"},{"name":"thumb_b2","parent":"thumb_a2","length":8.22,"x":10,"y":-0.06,"rotation":-14.56,"color":"848c00ff"},{"name":"finger_1_c","parent":"finger_1_b","length":4.86,"x":3.66,"y":0.01,"rotation":-0.45,"color":"ffd48bff"},{"name":"finger_1_c2","parent":"finger_1_b2","length":4.83,"x":3.66,"y":0.03,"rotation":-6.29,"color":"fff000ff"},{"name":"finger_1_c3","parent":"finger_1_b3","length":5,"x":3.79,"y":-0.01,"rotation":-0.45,"color":"069b00ff"},{"name":"finger_1_c4","parent":"finger_1_b4","length":5.04,"x":3.73,"rotation":8.5,"color":"5a9b78ff"},{"name":"finger_2_c","parent":"finger_2_b","length":4.48,"x":4.54,"rotation":-10.7,"color":"ff3f00ff"},{"name":"finger_2_c2","parent":"finger_2_b2","length":4.59,"x":4.64,"y":-0.02,"rotation":4.5,"color":"00549bff"}],"slots":[{"name":"effect_back_1","bone":"effect_back","color":"ffffff00"},{"name":"effect_back_2","bone":"effect_back","color":"ffffff00"},{"name":"effect_back_3","bone":"effect_back","color":"ffffff00"},{"name":"effect_back_4","bone":"effect_back","color":"ffffff00"},{"name":"effect_back_5","bone":"effect_back","color":"ffffff00"},{"name":"effect_back_6","bone":"effect_back","color":"ffffff00"},{"name":"effect_back_7","bone":"effect_back","color":"ffffff00"},{"name":"effect_back_8","bone":"effect_back","color":"ffffff00"},{"name":"effect_back_9","bone":"effect_back","color":"ffffff00"},{"name":"effect_back_10","bone":"effect_back","color":"ffffff00"},{"name":"effect_back_11","bone":"effect_back","color":"ffffff00"},{"name":"effect_back_12","bone":"effect_back","color":"ffffff00"},{"name":"effect_back_13","bone":"effect_back","color":"ffffff00"},{"name":"effect_back_14","bone":"effect_back","color":"ffffff00"},{"name":"effect_back_15","bone":"effect_back","color":"ffffff00"},{"name":"hair_outline","bone":"head_center"},{"name":"hair_behind","bone":"b_hair"},{"name":"hair_behind_static","bone":"head_center"},{"name":"hair_b","bone":"hair_b"},{"name":"hood","bone":"hood"},{"name":"R_arm_01","bone":"R_arm_01","attachment":"arm"},{"name":"R_arm_02","bone":"R_arm_02","attachment":"arm"},{"name":"R_arm_03","bone":"R_arm_03","attachment":"arm"},{"name":"R_arm_04","bone":"R_arm_04","attachment":"arm"},{"name":"R_arm_05","bone":"R_arm_05","attachment":"arm"},{"name":"R_arm_06","bone":"R_arm_06","attachment":"arm"},{"name":"R_arm_07","bone":"R_arm_07","attachment":"arm"},{"name":"R_arm_08","bone":"R_arm_08","attachment":"arm"},{"name":"R_arm_09","bone":"R_arm_09","attachment":"arm"},{"name":"R_arm_10","bone":"R_arm_10","attachment":"arm"},{"name":"R_arm_11","bone":"R_arm_11","attachment":"arm"},{"name":"R_arm_12","bone":"R_arm_12","attachment":"arm"},{"name":"R_arm_13","bone":"R_arm_13","attachment":"arm"},{"name":"R_arm_14","bone":"R_arm_14","attachment":"arm"},{"name":"R_arm_15","bone":"R_arm_15","attachment":"arm"},{"name":"R_arm_16","bone":"R_arm_16","attachment":"arm"},{"name":"R_object_1","bone":"R_object","color":"ffffff00"},{"name":"R_object_2","bone":"R_object","color":"ffffff00"},{"name":"R_object_3","bone":"R_object","color":"ffffff00"},{"name":"R_object_4","bone":"R_object","color":"ffffff00"},{"name":"R_object_5","bone":"R_object","color":"ffffff00"},{"name":"R_object_6","bone":"R_object","color":"ffffff00"},{"name":"R_object_7","bone":"R_object","color":"ffffff00"},{"name":"R_object_8","bone":"R_object","color":"ffffff00"},{"name":"R_object_9","bone":"R_object","color":"ffffff00"},{"name":"R_object_10","bone":"R_object","color":"ffffff00"},{"name":"R_object_11","bone":"R_object","color":"ffffff00"},{"name":"R_object_12","bone":"R_object","color":"ffffff00"},{"name":"R_object_13","bone":"R_object","color":"ffffff00"},{"name":"R_object_14","bone":"R_object","color":"ffffff00"},{"name":"R_object_15","bone":"R_object","color":"ffffff00"},{"name":"finger_2_a","bone":"finger_2_a","attachment":"finger_2_a"},{"name":"finger_2_b","bone":"finger_2_b","attachment":"finger_2_b"},{"name":"finger_2_c","bone":"finger_2_c","attachment":"finger_2_c"},{"name":"finger_1_a","bone":"finger_1_a2","attachment":"finger_1_a"},{"name":"finger_1_a2","bone":"finger_1_a22","attachment":"finger_1_a"},{"name":"finger_1_b","bone":"finger_1_b","attachment":"finger_1_b"},{"name":"finger_1_b2","bone":"finger_1_b2","attachment":"finger_1_b"},{"name":"finger_1_c","bone":"finger_1_c","attachment":"finger_1_c"},{"name":"finger_1_c2","bone":"finger_1_c2","attachment":"finger_1_c"},{"name":"thumb_a","bone":"thumb_a","attachment":"thumb_a"},{"name":"thumb_b","bone":"thumb_b","attachment":"thumb_b"},{"name":"hand","bone":"hand2","attachment":"hand"},{"name":"R_sleeve_b_01","bone":"R_arm_01"},{"name":"R_sleeve_b_02","bone":"R_arm_02"},{"name":"R_sleeve_b_03","bone":"R_arm_03"},{"name":"R_sleeve_b_04","bone":"R_arm_04"},{"name":"R_sleeve_b_05","bone":"R_arm_05"},{"name":"R_sleeve_b_06","bone":"R_arm_06"},{"name":"R_sleeve_b_07","bone":"R_arm_07"},{"name":"R_sleeve_b_08","bone":"R_arm_08"},{"name":"R_sleeve_b_09","bone":"R_arm_09"},{"name":"R_sleeve_b_10","bone":"R_arm_10"},{"name":"R_sleeve_b_11","bone":"R_arm_11"},{"name":"R_sleeve_b_12","bone":"R_arm_12"},{"name":"R_sleeve_b_13","bone":"R_arm_13"},{"name":"R_sleeve_b_14","bone":"R_arm_14"},{"name":"R_sleeve_b_15","bone":"R_arm_15"},{"name":"R_sleeve_b_16","bone":"R_arm_16"},{"name":"R_sleeve_01","bone":"R_arm_01"},{"name":"R_sleeve_02","bone":"R_arm_02"},{"name":"R_sleeve_03","bone":"R_arm_03"},{"name":"R_sleeve_04","bone":"R_arm_04"},{"name":"R_sleeve_05","bone":"R_arm_05"},{"name":"R_sleeve_06","bone":"R_arm_06"},{"name":"R_sleeve_07","bone":"R_arm_07"},{"name":"R_sleeve_08","bone":"R_arm_08"},{"name":"R_sleeve_09","bone":"R_arm_09"},{"name":"R_sleeve_10","bone":"R_arm_10"},{"name":"R_sleeve_11","bone":"R_arm_11"},{"name":"R_sleeve_12","bone":"R_arm_12"},{"name":"R_sleeve_13","bone":"R_arm_13"},{"name":"R_sleeve_14","bone":"R_arm_14"},{"name":"R_sleeve_15","bone":"R_arm_15"},{"name":"R_sleeve_16","bone":"R_arm_16"},{"name":"hip","bone":"hip"},{"name":"R_leg_1","bone":"R_leg_1","attachment":"leg"},{"name":"R_leg_2","bone":"R_leg_2","attachment":"leg"},{"name":"R_leg_3","bone":"R_leg_3","attachment":"leg"},{"name":"R_leg_4","bone":"R_leg_4","attachment":"leg"},{"name":"R_leg_5","bone":"R_leg_5","attachment":"leg"},{"name":"R_leg_6","bone":"R_leg_6","attachment":"leg"},{"name":"R_leg_7","bone":"R_leg_7","attachment":"leg"},{"name":"R_leg_8","bone":"R_leg_8","attachment":"leg"},{"name":"R_leg_9","bone":"R_leg_9","attachment":"leg"},{"name":"R_leg_10","bone":"R_leg_10","attachment":"leg"},{"name":"R_leg_11","bone":"R_leg_11","attachment":"leg"},{"name":"R_leg_12","bone":"R_leg_12","attachment":"leg"},{"name":"R_leg_end","bone":"R_leg_end","attachment":"leg"},{"name":"R_leg_13","bone":"R_leg_13","attachment":"leg"},{"name":"R_pants_b_1","bone":"R_leg_1"},{"name":"R_pants_b_2","bone":"R_leg_2"},{"name":"R_pants_b_3","bone":"R_leg_3"},{"name":"R_pants_b_4","bone":"R_leg_4"},{"name":"R_pants_b_5","bone":"R_leg_5"},{"name":"R_pants_b_6","bone":"R_leg_6"},{"name":"R_pants_b_7","bone":"R_leg_7"},{"name":"R_pants_b_8","bone":"R_leg_8"},{"name":"R_pants_b_9","bone":"R_leg_9"},{"name":"R_pants_b_10","bone":"R_leg_10"},{"name":"R_pants_b_11","bone":"R_leg_11"},{"name":"R_pants_b_12","bone":"R_leg_12"},{"name":"R_pants_b_13","bone":"R_leg_13"},{"name":"R_pants_1","bone":"R_leg_1"},{"name":"R_pants_2","bone":"R_leg_2"},{"name":"R_pants_3","bone":"R_leg_3"},{"name":"R_pants_4","bone":"R_leg_4"},{"name":"R_pants_5","bone":"R_leg_5"},{"name":"R_pants_6","bone":"R_leg_6"},{"name":"R_pants_7","bone":"R_leg_7"},{"name":"R_pants_8","bone":"R_leg_8"},{"name":"R_pants_9","bone":"R_leg_9"},{"name":"R_pants_10","bone":"R_leg_10"},{"name":"R_pants_11","bone":"R_leg_11"},{"name":"R_pants_12","bone":"R_leg_12"},{"name":"R_pants_13","bone":"R_leg_13"},{"name":"L_pants_b_1","bone":"L_leg_1"},{"name":"L_pants_b_2","bone":"L_leg_2"},{"name":"L_pants_b_3","bone":"L_leg_3"},{"name":"L_pants_b_4","bone":"L_leg_4"},{"name":"L_pants_b_5","bone":"L_leg_5"},{"name":"L_pants_b_6","bone":"L_leg_6"},{"name":"L_pants_b_7","bone":"L_leg_7"},{"name":"L_pants_b_8","bone":"L_leg_8"},{"name":"L_pants_b_9","bone":"L_leg_9"},{"name":"L_pants_b_10","bone":"L_leg_10"},{"name":"L_pants_b_11","bone":"L_leg_11"},{"name":"L_pants_b_12","bone":"L_leg_12"},{"name":"L_pants_b_13","bone":"L_leg_13"},{"name":"L_sleeve_b_01","bone":"L_arm_01"},{"name":"L_sleeve_b_02","bone":"L_arm_02"},{"name":"L_sleeve_b_03","bone":"L_arm_03"},{"name":"torso","bone":"torso","attachment":"torso"},{"name":"L_leg_1","bone":"L_leg_1","attachment":"leg"},{"name":"L_leg_2","bone":"L_leg_2","attachment":"leg"},{"name":"L_leg_3","bone":"L_leg_3","attachment":"leg"},{"name":"L_leg_4","bone":"L_leg_4","attachment":"leg"},{"name":"L_leg_5","bone":"L_leg_5","attachment":"leg"},{"name":"L_leg_6","bone":"L_leg_6","attachment":"leg"},{"name":"L_leg_7","bone":"L_leg_7","attachment":"leg"},{"name":"L_leg_8","bone":"L_leg_8","attachment":"leg"},{"name":"L_leg_9","bone":"L_leg_9","attachment":"leg"},{"name":"L_leg_10","bone":"L_leg_10","attachment":"leg"},{"name":"L_leg_11","bone":"L_leg_11","attachment":"leg"},{"name":"L_leg_12","bone":"L_leg_12","attachment":"leg"},{"name":"L_leg_end","bone":"L_leg_end","attachment":"leg"},{"name":"L_leg_13","bone":"L_leg_13","attachment":"leg"},{"name":"underwear","bone":"torso"},{"name":"pants_hip","bone":"torso"},{"name":"L_pants_1","bone":"L_leg_1"},{"name":"L_pants_2","bone":"L_leg_2"},{"name":"L_pants_3","bone":"L_leg_3"},{"name":"L_pants_4","bone":"L_leg_4"},{"name":"L_pants_5","bone":"L_leg_5"},{"name":"L_pants_6","bone":"L_leg_6"},{"name":"L_pants_7","bone":"L_leg_7"},{"name":"L_pants_8","bone":"L_leg_8"},{"name":"L_pants_9","bone":"L_leg_9"},{"name":"L_pants_10","bone":"L_leg_10"},{"name":"L_pants_11","bone":"L_leg_11"},{"name":"L_pants_12","bone":"L_leg_12"},{"name":"L_pants_13","bone":"L_leg_13"},{"name":"skirt_a2_low_back","bone":"skirt_a2_low"},{"name":"skirt_b2_low_back","bone":"skirt_b2_low"},{"name":"skirt_a1_low_back","bone":"skirt_a1_low"},{"name":"skirt_b1_low_back","bone":"skirt_b1_low"},{"name":"skirt_low_front_back","bone":"skirt_front_low"},{"name":"skirt_a2_back","bone":"skirt_a2"},{"name":"skirt_b2_back","bone":"skirt_b2"},{"name":"skirt_a1_back","bone":"skirt_a1"},{"name":"skirt_b1_back","bone":"skirt_b1"},{"name":"skirt_up_back","bone":"skirt_front"},{"name":"skirt_low_front_under","bone":"skirt_front_low"},{"name":"skirt_up_front_under","bone":"skirt_front"},{"name":"skirt_b2_low","bone":"skirt_b2_low"},{"name":"skirt_b2","bone":"skirt_b2"},{"name":"skirt_b1_low","bone":"skirt_b1_low"},{"name":"skirt_b1","bone":"skirt_b1"},{"name":"skirt_a2_low","bone":"skirt_a2_low"},{"name":"skirt_a2","bone":"skirt_a2"},{"name":"skirt_a1_low","bone":"skirt_a1_low"},{"name":"skirt_a1","bone":"skirt_a1"},{"name":"skirt_low_front","bone":"skirt_front_low"},{"name":"skirt_up_front","bone":"skirt_front"},{"name":"skirt_b2_low_over","bone":"skirt_b2_low"},{"name":"skirt_b2_over","bone":"skirt_b2"},{"name":"skirt_b1_low_over","bone":"skirt_b1_low"},{"name":"skirt_b1_over","bone":"skirt_b1"},{"name":"skirt_a2_low_over","bone":"skirt_a2_low"},{"name":"skirt_a2_over","bone":"skirt_a2"},{"name":"skirt_a1_low_over","bone":"skirt_a1_low"},{"name":"skirt_a1_over","bone":"skirt_a1"},{"name":"hip_skirt_rot","bone":"hip_skirt_rot"},{"name":"hip_skirt","bone":"hip"},{"name":"skirt_hip","bone":"torso"},{"name":"bra","bone":"torso"},{"name":"cloth","bone":"torso"},{"name":"R_earring","bone":"R_earring"},{"name":"head","bone":"head","attachment":"head"},{"name":"L_eyebug","bone":"L_eyebug","attachment":"eye_a"},{"name":"R_eyebug","bone":"R_eyebug","attachment":"eye_a"},{"name":"L_eye_light","bone":"L_eye_light"},{"name":"R_eye_light","bone":"R_eye_light"},{"name":"L_eye_ref","bone":"L_eye_ref"},{"name":"R_eye_ref","bone":"R_eye_ref"},{"name":"L_eyelid_lo","bone":"L_eyelid_lo","attachment":"eyelid"},{"name":"L_eyelid_up","bone":"L_eyelid_up","attachment":"eyelid"},{"name":"R_eyelid_lo","bone":"R_eyelid_lo","attachment":"eyelid"},{"name":"R_eyelid_up","bone":"R_eyelid_up","attachment":"eyelid"},{"name":"blush_L","bone":"blush_L","color":"ffffff00"},{"name":"blush_R","bone":"blush_R","color":"ffffff00"},{"name":"L_eyebrow_1","bone":"L_eyebrow_1","attachment":"face"},{"name":"mouth_upper","bone":"mouth_upper","attachment":"face"},{"name":"mouth_lower","bone":"mouth_lower","attachment":"face"},{"name":"R_eyebrow_1","bone":"R_eyebrow_1","attachment":"face"},{"name":"L_eyebrow_2","bone":"L_eyebrow_2","attachment":"face"},{"name":"L_mouth_up_1","bone":"L_mouth_up_1","attachment":"face"},{"name":"L_mouth_lo_1","bone":"L_mouth_lo_1","attachment":"face"},{"name":"R_mouth_up_1","bone":"R_mouth_up_1","attachment":"face"},{"name":"R_mouth_lo_1","bone":"R_mouth_lo_1","attachment":"face"},{"name":"R_eyebrow_2","bone":"R_eyebrow_2","attachment":"face"},{"name":"L_eyebrow_3","bone":"L_eyebrow_3","attachment":"face"},{"name":"L_mouth_up_2","bone":"L_mouth_up_2","attachment":"face"},{"name":"L_mouth_lo_2","bone":"L_mouth_lo_2","attachment":"face"},{"name":"R_mouth_up_2","bone":"R_mouth_up_2","attachment":"face"},{"name":"R_mouth_lo_2","bone":"R_mouth_lo_2","attachment":"face"},{"name":"R_eyebrow_3","bone":"R_eyebrow_3","attachment":"face"},{"name":"L_eyebrow_4","bone":"L_eyebrow_4","attachment":"face"},{"name":"L_mouth_up_3","bone":"L_mouth_up_3","attachment":"face"},{"name":"L_mouth_lo_3","bone":"L_mouth_lo_3","attachment":"face"},{"name":"R_mouth_up_3","bone":"R_mouth_up_3","attachment":"face"},{"name":"R_mouth_lo_3","bone":"R_mouth_lo_3","attachment":"face"},{"name":"R_eyebrow_4","bone":"R_eyebrow_4","attachment":"face"},{"name":"L_eyebrow_5","bone":"L_eyebrow_5","attachment":"face"},{"name":"L_mouth_up_4","bone":"L_mouth_up_4","attachment":"face"},{"name":"L_mouth_lo_4","bone":"L_mouth_lo_4","attachment":"face"},{"name":"L_mouth_up_5","bone":"L_mouth_up_5","attachment":"face"},{"name":"L_mouth_lo_5","bone":"L_mouth_lo_5","attachment":"face"},{"name":"R_mouth_up_4","bone":"R_mouth_up_4","attachment":"face"},{"name":"R_mouth_lo_4","bone":"R_mouth_lo_4","attachment":"face"},{"name":"R_mouth_up_5","bone":"R_mouth_up_5","attachment":"face"},{"name":"R_mouth_lo_5","bone":"R_mouth_lo_5","attachment":"face"},{"name":"R_eyebrow_5","bone":"R_eyebrow_5","attachment":"face"},{"name":"L_eyebrow_6","bone":"L_eyebrow_6","attachment":"face"},{"name":"R_eyebrow_6","bone":"R_eyebrow_6","attachment":"face"},{"name":"L_eyebrow_7","bone":"L_eyebrow_7","attachment":"face"},{"name":"R_eyebrow_7","bone":"R_eyebrow_7","attachment":"face"},{"name":"chin","bone":"chin"},{"name":"mouth_shapes","bone":"mouth_shapes"},{"name":"tongue","bone":"tongue"},{"name":"hair","bone":"head_center"},{"name":"glasses_a","bone":"glasses"},{"name":"glasses_b","bone":"glasses_b"},{"name":"L_earring","bone":"L_earring"},{"name":"tie","bone":"tie"},{"name":"scarf","bone":"torso"},{"name":"L_arm_01","bone":"L_arm_01","attachment":"arm"},{"name":"L_arm_02","bone":"L_arm_02","attachment":"arm"},{"name":"L_arm_03","bone":"L_arm_03","attachment":"arm"},{"name":"L_arm_04","bone":"L_arm_04","attachment":"arm"},{"name":"L_arm_05","bone":"L_arm_05","attachment":"arm"},{"name":"L_arm_06","bone":"L_arm_06","attachment":"arm"},{"name":"L_arm_07","bone":"L_arm_07","attachment":"arm"},{"name":"L_arm_08","bone":"L_arm_08","attachment":"arm"},{"name":"L_arm_09","bone":"L_arm_09","attachment":"arm"},{"name":"L_arm_10","bone":"L_arm_10","attachment":"arm"},{"name":"L_arm_11","bone":"L_arm_11","attachment":"arm"},{"name":"L_arm_12","bone":"L_arm_12","attachment":"arm"},{"name":"L_arm_13","bone":"L_arm_13","attachment":"arm"},{"name":"L_arm_14","bone":"L_arm_14","attachment":"arm"},{"name":"L_arm_15","bone":"L_arm_15","attachment":"arm"},{"name":"L_arm_16","bone":"L_arm_16","attachment":"arm"},{"name":"L_object_1","bone":"L_object","color":"ffffff00"},{"name":"L_object_2","bone":"L_object","color":"ffffff00"},{"name":"L_object_3","bone":"L_object","color":"ffffff00"},{"name":"L_object_4","bone":"L_object","color":"ffffff00"},{"name":"L_object_5","bone":"L_object","color":"ffffff00"},{"name":"L_object_6","bone":"L_object","color":"ffffff00"},{"name":"L_object_7","bone":"L_object","color":"ffffff00"},{"name":"L_object_8","bone":"L_object","color":"ffffff00"},{"name":"L_object_9","bone":"L_object","color":"ffffff00"},{"name":"L_object_10","bone":"L_object","color":"ffffff00"},{"name":"L_object_11","bone":"L_object","color":"ffffff00"},{"name":"L_object_12","bone":"L_object","color":"ffffff00"},{"name":"L_object_13","bone":"L_object","color":"ffffff00"},{"name":"L_object_14","bone":"L_object","color":"ffffff00"},{"name":"L_object_15","bone":"L_object","color":"ffffff00"},{"name":"finger_2_a2","bone":"finger_2_a2","attachment":"finger_2_a"},{"name":"finger_2_b2","bone":"finger_2_b2","attachment":"finger_2_b"},{"name":"finger_2_c2","bone":"finger_2_c2","attachment":"finger_2_c"},{"name":"finger_1_a3","bone":"finger_1_a23","attachment":"finger_1_a"},{"name":"finger_1_a4","bone":"finger_1_a24","attachment":"finger_1_a"},{"name":"finger_1_b3","bone":"finger_1_b3","attachment":"finger_1_b"},{"name":"finger_1_b4","bone":"finger_1_b4","attachment":"finger_1_b"},{"name":"finger_1_c3","bone":"finger_1_c3","attachment":"finger_1_c"},{"name":"finger_1_c4","bone":"finger_1_c4","attachment":"finger_1_c"},{"name":"thumb_a2","bone":"thumb_a2","attachment":"thumb_a"},{"name":"thumb_b2","bone":"thumb_b2","attachment":"thumb_b"},{"name":"hand2","bone":"hand22","attachment":"hand"},{"name":"L_sleeve_b_04","bone":"L_arm_04"},{"name":"L_sleeve_b_05","bone":"L_arm_05"},{"name":"L_sleeve_b_06","bone":"L_arm_06"},{"name":"L_sleeve_b_07","bone":"L_arm_07"},{"name":"L_sleeve_b_08","bone":"L_arm_08"},{"name":"L_sleeve_b_09","bone":"L_arm_09"},{"name":"L_sleeve_b_10","bone":"L_arm_10"},{"name":"L_sleeve_b_11","bone":"L_arm_11"},{"name":"L_sleeve_b_12","bone":"L_arm_12"},{"name":"L_sleeve_b_13","bone":"L_arm_13"},{"name":"L_sleeve_b_14","bone":"L_arm_14"},{"name":"L_sleeve_b_15","bone":"L_arm_15"},{"name":"L_sleeve_b_16","bone":"L_arm_16"},{"name":"L_sleeve_01","bone":"L_arm_01"},{"name":"L_sleeve_02","bone":"L_arm_02"},{"name":"L_sleeve_03","bone":"L_arm_03"},{"name":"L_sleeve_04","bone":"L_arm_04"},{"name":"L_sleeve_05","bone":"L_arm_05"},{"name":"L_sleeve_06","bone":"L_arm_06"},{"name":"L_sleeve_07","bone":"L_arm_07"},{"name":"L_sleeve_08","bone":"L_arm_08"},{"name":"L_sleeve_09","bone":"L_arm_09"},{"name":"L_sleeve_10","bone":"L_arm_10"},{"name":"L_sleeve_11","bone":"L_arm_11"},{"name":"L_sleeve_12","bone":"L_arm_12"},{"name":"L_sleeve_13","bone":"L_arm_13"},{"name":"L_sleeve_14","bone":"L_arm_14"},{"name":"L_sleeve_15","bone":"L_arm_15"},{"name":"L_sleeve_16","bone":"L_arm_16"},{"name":"hair_a","bone":"hair_a"},{"name":"hair_front_b","bone":"hair_front_b"},{"name":"hair_front_a","bone":"hair_front_a"},{"name":"hat","bone":"hat"},{"name":"effect_front_1","bone":"effect_front","color":"ffffff00"},{"name":"effect_front_2","bone":"effect_front","color":"ffffff00"},{"name":"effect_front_3","bone":"effect_front","color":"ffffff00"},{"name":"effect_front_4","bone":"effect_front","color":"ffffff00"},{"name":"effect_front_5","bone":"effect_front","color":"ffffff00"},{"name":"effect_front_6","bone":"effect_front","color":"ffffff00"},{"name":"effect_front_7","bone":"effect_front","color":"ffffff00"},{"name":"effect_front_8","bone":"effect_front","color":"ffffff00"},{"name":"effect_front_9","bone":"effect_front","color":"ffffff00"},{"name":"effect_front_10","bone":"effect_front","color":"ffffff00"},{"name":"effect_front_11","bone":"effect_front","color":"ffffff00"},{"name":"effect_front_12","bone":"effect_front","color":"ffffff00"},{"name":"effect_front_13","bone":"effect_front","color":"ffffff00"},{"name":"effect_front_14","bone":"effect_front","color":"ffffff00"},{"name":"effect_front_15","bone":"effect_front","color":"ffffff00"}],"skins":{"default":{"L_arm_01":{"arm":{"x":3.96,"y":-0.05,"width":18,"height":10}},"L_arm_02":{"arm":{"x":3.96,"y":-0.05,"width":18,"height":10}},"L_arm_03":{"arm":{"x":3.96,"y":-0.05,"width":18,"height":10}},"L_arm_04":{"arm":{"x":3.96,"y":-0.05,"width":18,"height":10}},"L_arm_05":{"arm":{"x":3.96,"y":-0.05,"width":18,"height":10}},"L_arm_06":{"arm":{"x":3.96,"y":-0.05,"width":18,"height":10}},"L_arm_07":{"arm":{"x":3.96,"y":-0.05,"width":18,"height":10}},"L_arm_08":{"arm":{"x":3.96,"y":-0.05,"width":18,"height":10}},"L_arm_09":{"arm":{"x":3.96,"y":-0.05,"width":18,"height":10}},"L_arm_10":{"arm":{"x":3.96,"y":-0.05,"width":18,"height":10}},"L_arm_11":{"arm":{"x":3.96,"y":-0.05,"width":18,"height":10}},"L_arm_12":{"arm":{"x":3.96,"y":-0.05,"width":18,"height":10}},"L_arm_13":{"arm":{"x":3.96,"y":-0.05,"width":18,"height":10}},"L_arm_14":{"arm":{"x":3.96,"y":-0.05,"width":18,"height":10}},"L_arm_15":{"arm":{"x":3.96,"y":-0.05,"width":18,"height":10}},"L_arm_16":{"arm":{"x":3.96,"y":-0.05,"width":18,"height":10}},"L_eye_light":{"eye_light":{"x":0.44,"y":-0.14,"scaleX":0.73,"scaleY":0.73,"rotation":-90,"width":11,"height":11}},"L_eye_ref":{"eye_light":{"x":0.44,"y":-0.14,"scaleX":0.4,"scaleY":0.4,"rotation":270,"width":11,"height":11}},"L_eyebrow_1":{"face":{"x":3.19,"y":0.09,"width":14,"height":9}},"L_eyebrow_2":{"face":{"x":3.19,"y":0.09,"width":14,"height":9}},"L_eyebrow_3":{"face":{"x":3.19,"y":0.09,"width":14,"height":9}},"L_eyebrow_4":{"face":{"x":3.19,"y":0.09,"width":14,"height":9}},"L_eyebrow_5":{"face":{"x":3.19,"y":0.09,"width":14,"height":9}},"L_eyebrow_6":{"face":{"x":3.19,"y":0.09,"width":14,"height":9}},"L_eyebrow_7":{"face":{"x":3.19,"y":0.09,"width":14,"height":9}},"L_eyebug":{"eye_a":{"x":0.53,"y":0.3,"scaleX":0.5,"scaleY":0.5,"rotation":-90,"width":33,"height":33},"eye_b":{"x":0.86,"y":0.3,"scaleX":0.775,"scaleY":0.775,"rotation":-90,"width":21,"height":7},"eye_c":{"x":0.8,"y":-0.37,"scaleX":0.769,"scaleY":0.769,"rotation":-90,"width":26,"height":17},"eye_d":{"x":-1.86,"y":0.04,"rotation":-90,"width":28,"height":11},"eye_x":{"x":0.35,"y":-0.76,"scaleX":0.787,"scaleY":0.787,"rotation":-90,"width":28,"height":19}},"L_leg_1":{"leg":{"x":3.9,"rotation":90,"width":10,"height":18}},"L_leg_10":{"leg":{"x":3.9,"rotation":90,"width":10,"height":18}},"L_leg_11":{"leg":{"x":3.9,"rotation":90,"width":10,"height":18}},"L_leg_12":{"leg":{"x":3.9,"rotation":90,"width":10,"height":18}},"L_leg_13":{"leg":{"x":3.9,"rotation":90,"width":10,"height":18}},"L_leg_2":{"leg":{"x":4.82,"rotation":90,"width":10,"height":18}},"L_leg_3":{"leg":{"x":3.9,"rotation":90,"width":10,"height":18}},"L_leg_4":{"leg":{"x":3.9,"rotation":90,"width":10,"height":18}},"L_leg_5":{"leg":{"x":3.9,"rotation":90,"width":10,"height":18}},"L_leg_6":{"leg":{"x":3.9,"rotation":90,"width":10,"height":18}},"L_leg_7":{"leg":{"x":3.9,"rotation":90,"width":10,"height":18}},"L_leg_8":{"leg":{"x":3.9,"rotation":90,"width":10,"height":18}},"L_leg_9":{"leg":{"x":3.9,"rotation":90,"width":10,"height":18}},"L_leg_end":{"leg":{"x":3.9,"rotation":90,"width":10,"height":18}},"L_mouth_lo_1":{"face":{"x":3.19,"y":0.09,"width":14,"height":9}},"L_mouth_lo_2":{"face":{"x":3.19,"y":0.09,"width":14,"height":9}},"L_mouth_lo_3":{"face":{"x":3.19,"y":0.09,"width":14,"height":9}},"L_mouth_lo_4":{"face":{"x":3.19,"y":0.09,"width":14,"height":9}},"L_mouth_lo_5":{"face":{"x":3.19,"y":0.09,"width":14,"height":9}},"L_mouth_up_1":{"face":{"x":3.19,"y":0.09,"width":14,"height":9}},"L_mouth_up_2":{"face":{"x":3.19,"y":0.09,"width":14,"height":9}},"L_mouth_up_3":{"face":{"x":3.19,"y":0.09,"width":14,"height":9}},"L_mouth_up_4":{"face":{"x":3.19,"y":0.09,"width":14,"height":9}},"L_mouth_up_5":{"face":{"x":3.19,"y":0.09,"width":14,"height":9}},"R_arm_01":{"arm":{"x":3.96,"y":-0.05,"width":18,"height":10}},"R_arm_02":{"arm":{"x":3.96,"y":-0.05,"width":18,"height":10}},"R_arm_03":{"arm":{"x":3.96,"y":-0.05,"width":18,"height":10}},"R_arm_04":{"arm":{"x":3.96,"y":-0.05,"width":18,"height":10}},"R_arm_05":{"arm":{"x":3.96,"y":-0.05,"width":18,"height":10}},"R_arm_06":{"arm":{"x":3.96,"y":-0.05,"width":18,"height":10}},"R_arm_07":{"arm":{"x":3.96,"y":-0.05,"width":18,"height":10}},"R_arm_08":{"arm":{"x":3.96,"y":-0.05,"width":18,"height":10}},"R_arm_09":{"arm":{"x":3.96,"y":-0.05,"width":18,"height":10}},"R_arm_10":{"arm":{"x":3.96,"y":-0.05,"width":18,"height":10}},"R_arm_11":{"arm":{"x":3.96,"y":-0.05,"width":18,"height":10}},"R_arm_12":{"arm":{"x":3.96,"y":-0.05,"width":18,"height":10}},"R_arm_13":{"arm":{"x":3.96,"y":-0.05,"width":18,"height":10}},"R_arm_14":{"arm":{"x":3.96,"y":-0.05,"width":18,"height":10}},"R_arm_15":{"arm":{"x":3.96,"y":-0.05,"width":18,"height":10}},"R_arm_16":{"arm":{"x":3.96,"y":-0.05,"width":18,"height":10}},"R_eye_light":{"eye_light":{"x":0.44,"y":-0.14,"scaleX":0.73,"scaleY":0.73,"rotation":-90,"width":11,"height":11}},"R_eye_ref":{"eye_light":{"x":0.44,"y":-0.14,"scaleX":0.4,"scaleY":0.4,"rotation":270,"width":11,"height":11}},"R_eyebrow_1":{"face":{"x":3.61,"y":0.09,"width":14,"height":9}},"R_eyebrow_2":{"face":{"x":3.19,"y":0.09,"width":14,"height":9}},"R_eyebrow_3":{"face":{"x":3.19,"y":0.09,"width":14,"height":9}},"R_eyebrow_4":{"face":{"x":3.19,"y":0.09,"width":14,"height":9}},"R_eyebrow_5":{"face":{"x":3.19,"y":0.09,"width":14,"height":9}},"R_eyebrow_6":{"face":{"x":3.19,"y":0.09,"width":14,"height":9}},"R_eyebrow_7":{"face":{"x":3.19,"y":0.09,"width":14,"height":9}},"R_eyebug":{"eye_a":{"x":0.39,"y":-0.22,"scaleX":0.504,"scaleY":0.504,"rotation":-90,"width":33,"height":33},"eye_b":{"x":0.72,"y":-0.22,"scaleX":0.783,"scaleY":0.783,"rotation":-90,"width":21,"height":7},"eye_c":{"x":0.66,"y":0.44,"scaleX":0.77,"scaleY":0.77,"rotation":90,"width":26,"height":17},"eye_d":{"x":-2,"y":-0.14,"rotation":-90,"width":28,"height":11},"eye_x":{"x":0.21,"y":-0.08,"scaleX":0.785,"scaleY":0.785,"rotation":-90,"width":28,"height":19}},"R_leg_1":{"leg":{"x":3.9,"rotation":90,"width":10,"height":18}},"R_leg_10":{"leg":{"x":3.9,"rotation":90,"width":10,"height":18}},"R_leg_11":{"leg":{"x":3.9,"rotation":90,"width":10,"height":18}},"R_leg_12":{"leg":{"x":3.9,"rotation":90,"width":10,"height":18}},"R_leg_13":{"leg":{"x":3.9,"rotation":90,"width":10,"height":18}},"R_leg_2":{"leg":{"x":3.9,"rotation":90,"width":10,"height":18}},"R_leg_3":{"leg":{"x":3.9,"rotation":90,"width":10,"height":18}},"R_leg_4":{"leg":{"x":3.9,"rotation":90,"width":10,"height":18}},"R_leg_5":{"leg":{"x":3.9,"rotation":90,"width":10,"height":18}},"R_leg_6":{"leg":{"x":3.9,"rotation":90,"width":10,"height":18}},"R_leg_7":{"leg":{"x":3.9,"rotation":90,"width":10,"height":18}},"R_leg_8":{"leg":{"x":3.9,"rotation":90,"width":10,"height":18}},"R_leg_9":{"leg":{"x":3.9,"rotation":90,"width":10,"height":18}},"R_leg_end":{"leg":{"x":3.9,"rotation":90,"width":10,"height":18}},"R_mouth_lo_1":{"face":{"x":3.19,"y":0.09,"width":14,"height":9}},"R_mouth_lo_2":{"face":{"x":3.19,"y":0.09,"width":14,"height":9}},"R_mouth_lo_3":{"face":{"x":3.19,"y":0.09,"width":14,"height":9}},"R_mouth_lo_4":{"face":{"x":3.19,"y":0.09,"width":14,"height":9}},"R_mouth_lo_5":{"face":{"x":3.19,"y":0.09,"width":14,"height":9}},"R_mouth_up_1":{"face":{"x":3.19,"y":0.09,"width":14,"height":9}},"R_mouth_up_2":{"face":{"x":3.19,"y":0.09,"width":14,"height":9}},"R_mouth_up_3":{"face":{"x":3.19,"y":0.09,"width":14,"height":9}},"R_mouth_up_4":{"face":{"x":3.19,"y":0.09,"width":14,"height":9}},"R_mouth_up_5":{"face":{"x":3.19,"y":0.09,"width":14,"height":9}},"blush_L":{"blush":{"x":1.88,"y":0.24,"rotation":-90,"width":40,"height":40}},"blush_R":{"blush":{"x":1.88,"y":0.24,"rotation":-90,"width":40,"height":40}},"chin":{"chin":{"x":0.29,"y":-1.46,"scaleX":-1,"width":20,"height":9}},"finger_1_a":{"finger_1_a":{"x":1.53,"y":0.12,"scaleX":0.586,"scaleY":0.586,"rotation":-0.41,"width":15,"height":8}},"finger_1_a2":{"finger_1_a":{"x":1.49,"y":0.1,"scaleX":0.586,"scaleY":0.586,"rotation":-0.38,"width":15,"height":8}},"finger_1_a3":{"finger_1_a":{"x":1.48,"y":0.1,"scaleX":0.6,"scaleY":0.6,"rotation":-1.36,"width":15,"height":8}},"finger_1_a4":{"finger_1_a":{"x":1.57,"y":0.11,"scaleX":0.6,"scaleY":0.6,"rotation":-0.55,"width":15,"height":8}},"finger_1_b":{"finger_1_b":{"x":2.07,"y":0.11,"scaleX":0.586,"scaleY":0.586,"rotation":0.07,"width":15,"height":8}},"finger_1_b2":{"finger_1_b":{"x":2.07,"y":0.13,"scaleX":0.586,"scaleY":0.586,"rotation":-0.32,"width":15,"height":8}},"finger_1_b3":{"finger_1_b":{"x":2.16,"y":0.13,"scaleX":0.6,"scaleY":0.6,"rotation":-0.46,"width":15,"height":8}},"finger_1_b4":{"finger_1_b":{"x":2.14,"y":0.14,"scaleX":0.6,"scaleY":0.6,"rotation":0.28,"width":15,"height":8}},"finger_1_c":{"finger_1_c":{"x":1.93,"y":0.03,"scaleX":0.586,"scaleY":0.586,"rotation":0.1,"width":15,"height":8}},"finger_1_c2":{"finger_1_c":{"x":1.93,"y":0.04,"scaleX":0.586,"scaleY":0.586,"rotation":0.63,"width":15,"height":8}},"finger_1_c3":{"finger_1_c":{"x":1.96,"y":0.06,"scaleX":0.6,"scaleY":0.6,"rotation":-0.01,"width":15,"height":8}},"finger_1_c4":{"finger_1_c":{"x":2.01,"y":0.07,"scaleX":0.6,"scaleY":0.6,"rotation":-0.2,"width":15,"height":8}},"finger_2_a":{"finger_2_a":{"x":2.06,"y":-0.19,"scaleX":0.586,"scaleY":0.586,"width":17,"height":9}},"finger_2_a2":{"finger_2_a":{"x":2.1,"y":-0.17,"scaleX":0.6,"scaleY":0.6,"rotation":-0.56,"width":17,"height":9}},"finger_2_b":{"finger_2_b":{"x":2.22,"y":-0.18,"scaleX":0.586,"scaleY":0.586,"rotation":0.45,"width":17,"height":9}},"finger_2_b2":{"finger_2_b":{"x":2.28,"y":-0.18,"scaleX":0.6,"scaleY":0.6,"rotation":-0.6,"width":17,"height":9}},"finger_2_c":{"finger_2_c":{"x":1.78,"y":-0.18,"scaleX":0.586,"scaleY":0.586,"rotation":-0.15,"width":15,"height":9}},"finger_2_c2":{"finger_2_c":{"x":1.84,"y":-0.19,"scaleX":0.6,"scaleY":0.6,"rotation":-0.27,"width":15,"height":9}},"hand":{"hand":{"x":8.05,"y":0.07,"scaleX":0.586,"scaleY":0.434,"width":45,"height":26}},"hand2":{"hand":{"x":8.24,"y":0.07,"scaleX":0.6,"scaleY":0.39,"width":45,"height":26}},"mouth_lower":{"face":{"x":0.57,"y":0.06,"width":14,"height":9}},"mouth_shapes":{"mouth_a":{"x":-11.92,"y":-5.46,"rotation":-90,"width":94,"height":45},"mouth_b":{"x":-7.42,"y":-6.96,"rotation":-94.97,"width":103,"height":63},"mouth_c":{"x":-9.42,"y":-4.46,"rotation":-90,"width":82,"height":26},"mouth_d":{"x":-8.21,"y":-10.13,"rotation":-93.99,"width":47,"height":31},"mouth_e":{"x":-4.1,"y":-8.68,"rotation":-90,"width":50,"height":53},"mouth_f":{"x":-3.36,"y":-9.83,"rotation":-90,"width":53,"height":49},"mouth_g":{"x":-7.2,"y":-3.9,"rotation":-90,"width":118,"height":61},"mouth_i":{"x":-6.11,"y":-4.94,"rotation":-90,"width":121,"height":47},"mouth_j":{"x":-6.1,"y":-4.95,"rotation":-90,"width":121,"height":47},"mouth_o":{"x":-8.92,"y":-18.96,"rotation":-90,"width":25,"height":25},"mouth_w_01":{"x":-3.66,"y":-6.94,"scaleX":0.66,"scaleY":0.66,"rotation":-90,"width":100,"height":30},"mouth_w_02":{"x":-3.66,"y":-6.94,"scaleX":0.661,"scaleY":0.661,"rotation":-90,"width":100,"height":30},"mouth_w_03":{"x":-3.66,"y":-6.94,"scaleX":0.661,"scaleY":0.661,"rotation":-90,"width":100,"height":30},"mouth_w_04":{"x":-3.66,"y":-6.94,"scaleX":0.661,"scaleY":0.661,"rotation":-90,"width":100,"height":30},"mouth_w_05":{"x":-3.66,"y":-6.94,"scaleX":0.661,"scaleY":0.661,"rotation":-90,"width":100,"height":30},"mouth_w_06":{"x":-3.66,"y":-6.94,"scaleX":0.661,"scaleY":0.661,"rotation":-90,"width":100,"height":30},"mouth_w_07":{"x":-3.66,"y":-6.94,"scaleX":0.661,"scaleY":0.661,"rotation":-90,"width":100,"height":30},"mouth_w_08":{"x":-3.66,"y":-6.94,"scaleX":0.661,"scaleY":0.661,"rotation":-90,"width":100,"height":30},"mouth_w_09":{"x":-3.66,"y":-6.94,"scaleX":0.661,"scaleY":0.661,"rotation":-90,"width":100,"height":30},"mouth_w_10":{"x":-3.66,"y":-6.94,"scaleX":0.661,"scaleY":0.661,"rotation":-90,"width":100,"height":30},"mouth_w_11":{"x":-3.66,"y":-6.94,"scaleX":0.661,"scaleY":0.661,"rotation":-90,"width":100,"height":30},"mouth_y":{"x":-6.31,"y":-12,"rotation":-90,"width":70,"height":11}},"mouth_upper":{"face":{"x":0.57,"y":0.06,"width":14,"height":9}},"thumb_a":{"thumb_a":{"x":4.89,"y":-0.11,"scaleX":0.586,"scaleY":0.586,"rotation":-36.16,"width":22,"height":19}},"thumb_a2":{"thumb_a":{"x":5,"y":-0.15,"scaleX":0.6,"scaleY":0.6,"rotation":-36.2,"width":22,"height":19}},"thumb_b":{"thumb_b":{"x":3.51,"y":0.06,"scaleX":0.586,"scaleY":0.586,"rotation":-40.85,"width":18,"height":17}},"thumb_b2":{"thumb_b":{"x":3.53,"y":0.08,"scaleX":0.6,"scaleY":0.6,"rotation":-40.56,"width":18,"height":17}},"tongue":{"tongue":{"x":-10.01,"y":-0.1,"rotation":-90,"width":30,"height":29}}},"boy_1":{"L_eyelid_lo":{"eyelid":{"name":"eyelid_1","x":3.1,"y":-14.85,"rotation":-90,"width":41,"height":15}},"L_eyelid_up":{"eyelid":{"name":"eyelid_1","x":3.1,"y":-14.85,"rotation":-90,"width":41,"height":15}},"R_eyelid_lo":{"eyelid":{"name":"eyelid_1","x":3.1,"y":14.9,"rotation":-90,"width":41,"height":15}},"R_eyelid_up":{"eyelid":{"name":"eyelid_1","x":3.1,"y":14.61,"rotation":-90,"width":41,"height":15}},"head":{"head":{"name":"head_1","x":79.91,"y":0.98,"rotation":-90,"width":181,"height":181}},"torso":{"torso":{"name":"boy_1","x":45.79,"rotation":-90,"width":80,"height":134}}},"boy_2":{"L_eyelid_lo":{"eyelid":{"name":"eyelid_2","x":3.1,"y":-14.85,"rotation":-90,"width":41,"height":15}},"L_eyelid_up":{"eyelid":{"name":"eyelid_2","x":3.1,"y":-14.85,"rotation":-90,"width":41,"height":15}},"R_eyelid_lo":{"eyelid":{"name":"eyelid_2","x":3.1,"y":14.9,"rotation":-90,"width":41,"height":15}},"R_eyelid_up":{"eyelid":{"name":"eyelid_2","x":3.1,"y":14.61,"rotation":-90,"width":41,"height":15}},"head":{"head":{"name":"head_2","x":79.91,"y":0.98,"rotation":-90,"width":181,"height":181}},"torso":{"torso":{"name":"boy_2","x":45.79,"rotation":-90,"width":80,"height":134}}},"boy_3":{"L_eyelid_lo":{"eyelid":{"name":"eyelid_3","x":3.1,"y":-14.85,"rotation":-90,"width":41,"height":15}},"L_eyelid_up":{"eyelid":{"name":"eyelid_3","x":3.1,"y":-14.85,"rotation":-90,"width":41,"height":15}},"R_eyelid_lo":{"eyelid":{"name":"eyelid_3","x":3.1,"y":14.9,"rotation":-90,"width":41,"height":15}},"R_eyelid_up":{"eyelid":{"name":"eyelid_3","x":3.1,"y":14.61,"rotation":-90,"width":41,"height":15}},"head":{"head":{"name":"head_3","x":79.91,"y":0.98,"rotation":-90,"width":181,"height":181}},"torso":{"torso":{"name":"boy_3","x":45.79,"rotation":-90,"width":80,"height":134}}},"boy_4":{"L_eyelid_lo":{"eyelid":{"name":"eyelid_4","x":3.1,"y":-14.85,"rotation":-90,"width":41,"height":15}},"L_eyelid_up":{"eyelid":{"name":"eyelid_4","x":3.1,"y":-14.85,"rotation":-90,"width":41,"height":15}},"R_eyelid_lo":{"eyelid":{"name":"eyelid_4","x":3.1,"y":14.9,"rotation":-90,"width":41,"height":15}},"R_eyelid_up":{"eyelid":{"name":"eyelid_4","x":3.1,"y":14.61,"rotation":-90,"width":41,"height":15}},"head":{"head":{"name":"head_4","x":79.91,"y":0.98,"rotation":-90,"width":181,"height":181}},"torso":{"torso":{"name":"boy_4","x":45.79,"rotation":-90,"width":80,"height":134}}},"boy_5":{"L_eyelid_lo":{"eyelid":{"name":"eyelid_5","x":3.1,"y":-14.85,"rotation":-90,"width":41,"height":15}},"L_eyelid_up":{"eyelid":{"name":"eyelid_5","x":3.1,"y":-14.85,"rotation":-90,"width":41,"height":15}},"R_eyelid_lo":{"eyelid":{"name":"eyelid_5","x":3.1,"y":14.9,"rotation":-90,"width":41,"height":15}},"R_eyelid_up":{"eyelid":{"name":"eyelid_5","x":3.1,"y":14.61,"rotation":-90,"width":41,"height":15}},"head":{"head":{"name":"head_5","x":79.91,"y":0.98,"rotation":-90,"width":181,"height":181}},"torso":{"torso":{"name":"boy_5","x":45.79,"rotation":-90,"width":80,"height":134}}},"boy_6":{"L_eyelid_lo":{"eyelid":{"name":"eyelid_6","x":3.1,"y":-14.85,"rotation":-90,"width":41,"height":15}},"L_eyelid_up":{"eyelid":{"name":"eyelid_6","x":3.1,"y":-14.85,"rotation":-90,"width":41,"height":15}},"R_eyelid_lo":{"eyelid":{"name":"eyelid_6","x":3.1,"y":14.9,"rotation":-90,"width":41,"height":15}},"R_eyelid_up":{"eyelid":{"name":"eyelid_6","x":3.1,"y":14.61,"rotation":-90,"width":41,"height":15}},"head":{"head":{"name":"head_6","x":79.91,"y":0.98,"rotation":-90,"width":181,"height":181}},"torso":{"torso":{"name":"boy_6","x":45.79,"rotation":-90,"width":80,"height":134}}},"girl_1":{"L_eyelid_lo":{"eyelid":{"name":"eyelid_1","x":3.1,"y":-14.85,"rotation":-90,"width":41,"height":15}},"L_eyelid_up":{"eyelid":{"name":"eyelid_1","x":3.1,"y":-14.85,"rotation":-90,"width":41,"height":15}},"R_eyelid_lo":{"eyelid":{"name":"eyelid_1","x":3.1,"y":14.9,"rotation":-90,"width":41,"height":15}},"R_eyelid_up":{"eyelid":{"name":"eyelid_1","x":3.1,"y":14.61,"rotation":-90,"width":41,"height":15}},"head":{"head":{"name":"head_1","x":79.91,"y":0.98,"rotation":-90,"width":181,"height":181}},"torso":{"torso":{"name":"girl_1","x":46.51,"y":-1,"rotation":-90,"width":75,"height":135}}},"girl_2":{"L_eyelid_lo":{"eyelid":{"name":"eyelid_2","x":3.1,"y":-14.85,"rotation":-90,"width":41,"height":15}},"L_eyelid_up":{"eyelid":{"name":"eyelid_2","x":3.1,"y":-14.85,"rotation":-90,"width":41,"height":15}},"R_eyelid_lo":{"eyelid":{"name":"eyelid_2","x":3.1,"y":14.9,"rotation":-90,"width":41,"height":15}},"R_eyelid_up":{"eyelid":{"name":"eyelid_2","x":3.1,"y":14.61,"rotation":-90,"width":41,"height":15}},"head":{"head":{"name":"head_2","x":79.91,"y":0.98,"rotation":-90,"width":181,"height":181}},"torso":{"torso":{"name":"girl_2","x":46.51,"y":-1,"rotation":-90,"width":75,"height":135}}},"girl_3":{"L_eyelid_lo":{"eyelid":{"name":"eyelid_3","x":3.1,"y":-14.85,"rotation":-90,"width":41,"height":15}},"L_eyelid_up":{"eyelid":{"name":"eyelid_3","x":3.1,"y":-14.85,"rotation":-90,"width":41,"height":15}},"R_eyelid_lo":{"eyelid":{"name":"eyelid_3","x":3.1,"y":14.9,"rotation":-90,"width":41,"height":15}},"R_eyelid_up":{"eyelid":{"name":"eyelid_3","x":3.1,"y":14.61,"rotation":-90,"width":41,"height":15}},"head":{"head":{"name":"head_3","x":79.91,"y":0.98,"rotation":-90,"width":181,"height":181}},"torso":{"torso":{"name":"girl_3","x":46.51,"y":-1,"rotation":-90,"width":75,"height":135}}},"girl_4":{"L_eyelid_lo":{"eyelid":{"name":"eyelid_4","x":3.1,"y":-14.85,"rotation":-90,"width":41,"height":15}},"L_eyelid_up":{"eyelid":{"name":"eyelid_4","x":3.1,"y":-14.85,"rotation":-90,"width":41,"height":15}},"R_eyelid_lo":{"eyelid":{"name":"eyelid_4","x":3.1,"y":14.9,"rotation":-90,"width":41,"height":15}},"R_eyelid_up":{"eyelid":{"name":"eyelid_4","x":3.1,"y":14.61,"rotation":-90,"width":41,"height":15}},"head":{"head":{"name":"head_4","x":79.91,"y":0.98,"rotation":-90,"width":181,"height":181}},"torso":{"torso":{"name":"girl_4","x":46.51,"y":-1,"rotation":-90,"width":75,"height":135}}},"girl_5":{"L_eyelid_lo":{"eyelid":{"name":"eyelid_5","x":3.1,"y":-14.85,"rotation":-90,"width":41,"height":15}},"L_eyelid_up":{"eyelid":{"name":"eyelid_5","x":3.1,"y":-14.85,"rotation":-90,"width":41,"height":15}},"R_eyelid_lo":{"eyelid":{"name":"eyelid_5","x":3.1,"y":14.9,"rotation":-90,"width":41,"height":15}},"R_eyelid_up":{"eyelid":{"name":"eyelid_5","x":3.1,"y":14.61,"rotation":-90,"width":41,"height":15}},"head":{"head":{"name":"head_5","x":79.91,"y":0.98,"rotation":-90,"width":181,"height":181}},"torso":{"torso":{"name":"girl_5","x":46.51,"y":-1,"rotation":-90,"width":75,"height":135}}},"girl_6":{"L_eyelid_lo":{"eyelid":{"name":"eyelid_6","x":3.1,"y":-14.85,"rotation":-90,"width":41,"height":15}},"L_eyelid_up":{"eyelid":{"name":"eyelid_6","x":3.1,"y":-14.85,"rotation":-90,"width":41,"height":15}},"R_eyelid_lo":{"eyelid":{"name":"eyelid_6","x":3.1,"y":14.9,"rotation":-90,"width":41,"height":15}},"R_eyelid_up":{"eyelid":{"name":"eyelid_6","x":3.1,"y":14.61,"rotation":-90,"width":41,"height":15}},"head":{"head":{"name":"head_6","x":79.91,"y":0.98,"rotation":-90,"width":181,"height":181}},"torso":{"torso":{"name":"girl_6","x":46.51,"y":-1,"rotation":-90,"width":75,"height":135}}}}}